llama_index/embeddings/instructor/__init__.py
llama_index/embeddings/instructor/base.py
llama_index/embeddings/instructor/utils.py
llama_index_embeddings_instructor-0.4.1.dist-info/METADATA
llama_index_embeddings_instructor-0.4.1.dist-info/WHEEL
llama_index_embeddings_instructor-0.4.1.dist-info/licenses/LICENSE
llama_index_embeddings_instructor-0.4.1.dist-info/RECORD
