Metadata-Version: 2.4
Name: llama-index-embeddings-instructor
Version: 0.4.1
Summary: llama-index embeddings instructor integration
Author-email: Your Name <you@example.com>
License-Expression: MIT
License-File: LICENSE
Requires-Python: <4.0,>=3.9
Requires-Dist: instructorembedding<2,>=1.0.1
Requires-Dist: llama-index-core<0.15,>=0.13.0
Requires-Dist: sentence-transformers<3,>=2.2.2
Requires-Dist: torch<3,>=2.1.2
